miupload/__init__.py
miupload/miupload.py
miupload/runningConfiguration.py
miupload/skins.py
miupload_pkg/__init__.py
miupload_pkg/miupload.py
miupload_pkg/runningConfiguration.py
miupload-1.6.2.dist-info/LICENSE
miupload-1.6.2.dist-info/METADATA
miupload-1.6.2.dist-info/WHEEL
miupload-1.6.2.dist-info/top_level.txt
miupload-1.6.2.dist-info/RECORD
