Metadata-Version: 2.1
Name: miupload
Version: 1.6.2
Summary: Small lighweight library for collecting and distribution of jupyter notebooks during SSS on MSaKGI.
Home-page: https://github.com/pypa/sampleproject
Author: Juraj Vasek
Author-email: juraj.vasek@minerva.kgi.edu
License: MIT
Platform: UNKNOWN
Classifier: Programming Language :: Python :: 3
Classifier: License :: OSI Approved :: MIT License
Classifier: Operating System :: OS Independent
Requires-Python: >=3
Requires-Dist: requests
Requires-Dist: ipykernel
Requires-Dist: ipython
